setup.py
AreaCode.egg-info/PKG-INFO
AreaCode.egg-info/SOURCES.txt
AreaCode.egg-info/dependency_links.txt
AreaCode.egg-info/top_level.txt
ChinaArea/AreaCode.py
ChinaArea/__init__.py