Metadata-Version: 1.0
Name: AreaCode
Version: 1.0.0
Summary: China area code list
Home-page: UNKNOWN
Author: Alvin Ren
Author-email: renqingmail@126.com
License: MIT License
Keywords: china,area,code
Platform: any
